patent_parsing_tools/__init__.py
patent_parsing_tools/downloader.py
patent_parsing_tools/extractor.py
patent_parsing_tools/patent.py
patent_parsing_tools/splitter.py
patent_parsing_tools/supervisor.py
patent_parsing_tools/unzipper.py
patent_parsing_tools/bow/__init__.py
patent_parsing_tools/bow/bag_of_words.py
patent_parsing_tools/bow/conftest.py
patent_parsing_tools/bow/dictionary_maker.py
patent_parsing_tools/bow/wordcount.py
patent_parsing_tools/bow/tests/__init__.py
patent_parsing_tools/bow/tests/dictionary.txt
patent_parsing_tools/bow/tests/test_bag_of_words.py
patent_parsing_tools/bow/tests/test_dictionary_maker.py
patent_parsing_tools/bow/tests/test_wordcount.py
patent_parsing_tools/config/__init__.py
patent_parsing_tools/config/extractor_configuration.json
patent_parsing_tools/tests/US08613112-20131224.XML
patent_parsing_tools/tests/US08613112-lackofnode.XML
patent_parsing_tools/tests/US08613112-noDTDFile.XML
patent_parsing_tools/tests/US08613112-notSupportedDTD.XML
patent_parsing_tools/tests/US08927386-20150106.XML
patent_parsing_tools/tests/__init__.py
patent_parsing_tools/tests/test_downloader.py
patent_parsing_tools/tests/test_extractor.py
patent_parsing_tools/tests/test_patent.py
patent_parsing_tools/utils/__init__.py
patent_parsing_tools/utils/fmatrix.py
patent_parsing_tools/utils/log.py
patent_parsing_tools/utils/tests/__init__.py
patent_parsing_tools/utils/tests/dictionary.txt
patent_parsing_tools/utils/tests/test_fmatrix.py
patent_parsing_tools/utils/tests/test_log.py
patent_parsing_tools/utils/tests/train.txt
patent_parsing_tools-0.9.5.dist-info/LICENSE.txt
patent_parsing_tools-0.9.5.dist-info/METADATA
patent_parsing_tools-0.9.5.dist-info/WHEEL
patent_parsing_tools-0.9.5.dist-info/top_level.txt
patent_parsing_tools-0.9.5.dist-info/RECORD
