Metadata-Version: 2.1
Name: patent-parsing-tools
Version: 0.9.5
Summary: patent-parsing-tools is a library providing tools for generating training and test set from Google's USPTO data helpful with for testing machine learning algorithms
Home-page: https://github.com/pprzetacznik/patent-parsing-tools
Author: Michal Dul, Piotr Przetacznik, Krzysztof Strojny
Author-email: piotr.przetacznik@gmail.com
License: MIT
Keywords: deeplearning dbn rbm rsm backpropagation precission recall
Platform: UNKNOWN
Classifier: Development Status :: 5 - Production/Stable
Classifier: Intended Audience :: Developers
Classifier: Topic :: Utilities
Classifier: License :: OSI Approved :: MIT License
Classifier: Programming Language :: Python :: 3.8
Requires-Dist: lxml
Requires-Dist: nltk
Requires-Dist: stemming
Requires-Dist: Sphinx
Requires-Dist: sphinx-rtd-theme
Requires-Dist: requests
Requires-Dist: numpy==1.22.0
Requires-Dist: Theano==0.9.0
Requires-Dist: mypy
Requires-Dist: pytest
Requires-Dist: pytest-cov
